segment3D/__init__.py
segment3D/file_io.py
segment3D/filters.py
segment3D/flows.py
segment3D/gpu.py
segment3D/meshtools.py
segment3D/metrics.py
segment3D/parameters.py
segment3D/plotting.py
segment3D/segmentation.py
segment3D/usegment3d.py
segment3D/watershed.py
u_segment3d-0.1.3.dist-info/licenses/LICENSE
u_segment3d-0.1.3.dist-info/METADATA
u_segment3d-0.1.3.dist-info/WHEEL
u_segment3d-0.1.3.dist-info/top_level.txt
u_segment3d-0.1.3.dist-info/RECORD
