Metadata-Version: 2.4
Name: u-Segment3D
Version: 0.1.3
Summary: Generate consensus 3D segmentation from 2D segmented stacks
Author-email: "Felix Y. Zhou" <felixzhou1@gmail.com>
License:                     GNU GENERAL PUBLIC LICENSE
Project-URL: Homepage, https://github.com/DanuserLab/u-segment3D
Project-URL: Issues, https://github.com/DanuserLab/u-segment3D/issues
Classifier: Intended Audience :: Developers
Classifier: Operating System :: POSIX :: Linux
Classifier: Operating System :: MacOS :: MacOS X
Classifier: Operating System :: Microsoft :: Windows
Classifier: Programming Language :: Python :: 3.9
Classifier: Programming Language :: Python :: 3.10
Classifier: Programming Language :: Python :: 3.11
Classifier: Programming Language :: Python :: 3.12
Requires-Python: <3.13,>=3.9
License-File: LICENSE
Requires-Dist: numpy<2.0
Requires-Dist: pyarrow<21
Requires-Dist: cellpose<4.0
Requires-Dist: cupy-cuda11x; sys_platform != "darwin"
Requires-Dist: dask[complete]
Requires-Dist: scikit-image
Requires-Dist: scikit-learn
Requires-Dist: imagecodecs<2025
Requires-Dist: contourpy<=1.2.0
Requires-Dist: opencv-python-headless
Requires-Dist: scipy
Requires-Dist: numba
Requires-Dist: matplotlib
Requires-Dist: seaborn
Requires-Dist: trimesh
Requires-Dist: multiprocess
Requires-Dist: tiler
Requires-Dist: connected-components-3d
Requires-Dist: edt
Requires-Dist: tqdm
Requires-Dist: scikit-fmm; sys_platform == "win"
Requires-Dist: czifile
Dynamic: license-file
